PyU4V/__init__.py
PyU4V/clone.py
PyU4V/common.py
PyU4V/metro_dr.py
PyU4V/migration.py
PyU4V/performance.py
PyU4V/performance_enhanced.py
PyU4V/provisioning.py
PyU4V/real_time.py
PyU4V/replication.py
PyU4V/rest_requests.py
PyU4V/serviceability.py
PyU4V/snapshot_policy.py
PyU4V/storage_groups.py
PyU4V/system.py
PyU4V/univmax_conn.py
PyU4V/volumes.py
PyU4V/workload_planner.py
PyU4V/tools/__init__.py
PyU4V/tools/generate_functions.py
PyU4V/tools/openstack/__init__.py
PyU4V/tools/openstack/migrate.py
PyU4V/tools/openstack/migrate_utils.py
PyU4V/utils/__init__.py
PyU4V/utils/config_handler.py
PyU4V/utils/console.py
PyU4V/utils/constants.py
PyU4V/utils/decorators.py
PyU4V/utils/exception.py
PyU4V/utils/file_handler.py
PyU4V/utils/performance_category_map.py
PyU4V/utils/performance_constants.py
PyU4V/utils/time_handler.py
PyU4V/utils/utils.py
PyU4V-10.2.0.0.dist-info/LICENSE
PyU4V-10.2.0.0.dist-info/METADATA
PyU4V-10.2.0.0.dist-info/WHEEL
PyU4V-10.2.0.0.dist-info/top_level.txt
PyU4V-10.2.0.0.dist-info/RECORD
