Metadata-Version: 2.1
Name: PyU4V
Version: 10.2.0.0
Summary: A Python library for use with Dell EMC's Unisphere for PowerMax REST API.
Home-page: https://github.com/dell/PyU4V/
Author: Dell Inc. or its subsidiaries
Author-email: paule.martin@dell.com
License: Apache 2.0
Platform: UNKNOWN
Classifier: Development Status :: 5 - Production/Stable
Classifier: Intended Audience :: Developers
Classifier: Intended Audience :: System Administrators
Classifier: License :: OSI Approved :: MIT License
Classifier: Operating System :: OS Independent
Classifier: Programming Language :: Python
Classifier: Programming Language :: Python :: 3.6
Classifier: Programming Language :: Python :: 3.7
Classifier: Programming Language :: Python :: 3.8
Classifier: Programming Language :: Python :: 3.9
Classifier: Topic :: Internet :: WWW/HTTP
Classifier: Topic :: Software Development :: Libraries :: Python Modules
Requires-Python: >=3.6, <4.0
License-File: LICENSE
Requires-Dist: requests
Requires-Dist: six
Requires-Dist: urllib3
Requires-Dist: prettytable
